{"number":48,"id":"011010","hex":"䷯","title":{"fanti":"井","jianti":"井","pinyin":"jǐng","wadeGiles":"Ching","english":"The Well"},"structure":{"above":"kan","below":"sun"},"description":"","meta":{"host":[{"line":6,"governingRuler":true}],"element":"water","month":{"lunar":5,"solar":"June"},"relationships":{"opposite":21,"inverse":47,"mutual":38}},"judgement":{"text":"井：改邑不改井，無喪無得，往來井井。汔至，亦未繘井，羸其瓶，凶。","commentary":"彖曰：巽乎水而上水，井；井養而不窮也。改邑不改井，乃以剛中也。汔至亦未繘井，未有功也。羸其瓶，是以凶也。"},"image":{"text":"象曰：木上有水，井；君子以勞民勸相。","commentary":""},"lines":[{"number":1,"host":false,"text":"初六：井泥不食，舊井無禽。","commentary":"象曰：井泥不食，下也。舊井無禽，時舍也。"},{"number":2,"host":false,"text":"九二：井谷射鮒，甕敝漏。","commentary":"象曰：井谷射鮒，無與也。"},{"number":3,"host":false,"text":"九三：井渫不食，為我民惻，可用汲，王明，並受其福。","commentary":"象曰：井渫不食，行惻也。求王明，受福也。"},{"number":4,"host":false,"text":"六四：井甃，無咎。","commentary":"象曰：井甃無咎，修井也。"},{"number":5,"host":false,"text":"九五：井冽，寒泉食。","commentary":"象曰：寒泉之食，中正也。"},{"number":6,"host":true,"text":"上六：井收勿幕，有孚無吉。","commentary":"象曰：元吉在上，大成也。"}]}